sbilby/__init__.py
sbilby/_version.py
sbilby/data_generation.py
sbilby/simulation_based_inference.py
sbilby/simulation_based_inference_multidetector.py
sbilby/simulation_based_inference_multidetector_realData.py
sbilby-0.0.1.dist-info/licenses/LICENSE
sbilby-0.0.1.dist-info/METADATA
sbilby-0.0.1.dist-info/WHEEL
sbilby-0.0.1.dist-info/top_level.txt
sbilby-0.0.1.dist-info/RECORD
