Metadata-Version: 2.4
Name: sbilby
Version: 0.0.1
Summary: A package to perform residual neural likelihood evaluation for gravitational waves
License: MIT
Project-URL: Homepage, https://github.com/MattiaEmma2022/sbilby
Project-URL: Issues, https://github.com/MattiaEmma2022/sbilby/issues
Classifier: Programming Language :: Python :: 3
Classifier: Operating System :: OS Independent
Requires-Python: >=3.9
License-File: LICENSE
Dynamic: license-file
